LICENSE
MANIFEST.in
README.rst
requirements.txt
setup.py
sphinx_drove_theme/__init__.py
sphinx_drove_theme/breadcrumbs.html
sphinx_drove_theme/footer.html
sphinx_drove_theme/layout.html
sphinx_drove_theme/layout_old.html
sphinx_drove_theme/search.html
sphinx_drove_theme/searchbox.html
sphinx_drove_theme/theme.conf
sphinx_drove_theme/versions.html
sphinx_drove_theme.egg-info/PKG-INFO
sphinx_drove_theme.egg-info/SOURCES.txt
sphinx_drove_theme.egg-info/dependency_links.txt
sphinx_drove_theme.egg-info/not-zip-safe
sphinx_drove_theme.egg-info/requires.txt
sphinx_drove_theme.egg-info/top_level.txt
sphinx_drove_theme/static/favicon.png
sphinx_drove_theme/static/css/badge_only.css
sphinx_drove_theme/static/css/main.css
sphinx_drove_theme/static/css/theme.css
sphinx_drove_theme/static/fonts/fontawesome-webfont.eot
sphinx_drove_theme/static/fonts/fontawesome-webfont.svg
sphinx_drove_theme/static/fonts/fontawesome-webfont.ttf
sphinx_drove_theme/static/fonts/fontawesome-webfont.woff
sphinx_drove_theme/static/fonts/logo.eot
sphinx_drove_theme/static/fonts/logo.svg
sphinx_drove_theme/static/fonts/logo.ttf
sphinx_drove_theme/static/fonts/logo.woff
sphinx_drove_theme/static/js/theme.js