Metadata-Version: 1.1
Name: sphinx_drove_theme
Version: 1.11.0
Summary: drove.io theme for Sphinx, 2014 version.
Home-page: https://github.com/droveio/sphinx-drove-theme
Author: Andrés J. Díaz
Author-email: ajdiaz@connectical.com
License: MIT
Platform: UNKNOWN
Classifier: Development Status :: 3 - Alpha
Classifier: License :: OSI Approved :: BSD License
Classifier: Environment :: Console
Classifier: Environment :: Web Environment
Classifier: Intended Audience :: Developers
Classifier: Programming Language :: Python :: 2.7
Classifier: Programming Language :: Python :: 3
Classifier: Operating System :: OS Independent
Classifier: Topic :: Documentation
Classifier: Topic :: Software Development :: Documentation
